Metadata-Version: 2.4
Name: adaptive-k
Version: 0.1.2
Summary: Entropy-guided dynamic expert selection for MoE models. Reduce inference costs by 30-50%.
Author-email: Vertex Data <amministrazione@vertexdata.it>
Maintainer-email: Gabriele Balsamo <amministrazione@vertexdata.it>
License-Expression: Apache-2.0
Project-URL: Homepage, https://adaptive-k.vertexdata.it
Project-URL: Documentation, https://github.com/Gabrobals/sbm-efficient/tree/master/sdk
Project-URL: Repository, https://github.com/Gabrobals/sbm-efficient
Project-URL: Issues, https://github.com/Gabrobals/sbm-efficient/issues
Keywords: moe,mixture-of-experts,adaptive-k,inference-optimization,llm,tensorrt,pytorch,transformers,cost-reduction,enterprise
Classifier: Development Status :: 3 - Alpha
Classifier: Intended Audience :: Developers
Classifier: Intended Audience :: Science/Research
Classifier: Programming Language :: Python :: 3
Classifier: Programming Language :: Python :: 3.9
Classifier: Programming Language :: Python :: 3.10
Classifier: Programming Language :: Python :: 3.11
Classifier: Programming Language :: Python :: 3.12
Classifier: Topic :: Scientific/Engineering :: Artificial Intelligence
Requires-Python: >=3.9
License-File: LICENSE
Requires-Dist: torch>=2.0.0
Requires-Dist: numpy>=1.21.0
Provides-Extra: dev
Requires-Dist: pytest>=7.0.0; extra == "dev"
Requires-Dist: pytest-cov>=4.0.0; extra == "dev"
Requires-Dist: black>=23.0.0; extra == "dev"
Requires-Dist: ruff>=0.1.0; extra == "dev"
Requires-Dist: mypy>=1.0.0; extra == "dev"
Provides-Extra: huggingface
Requires-Dist: transformers>=4.30.0; extra == "huggingface"
Requires-Dist: datasets>=2.0.0; extra == "huggingface"
Provides-Extra: vllm
Requires-Dist: vllm>=0.2.0; extra == "vllm"
Provides-Extra: all
Requires-Dist: adaptive-k[dev,huggingface,vllm]; extra == "all"
Dynamic: license-file
